pyaztro/__init__.py
pyaztro/aztro.py
pyaztro/exceptions.py
pyaztro/helpers.py
pyaztro/models.py
pyaztro-0.3.dist-info/LICENSE
pyaztro-0.3.dist-info/METADATA
pyaztro-0.3.dist-info/WHEEL
pyaztro-0.3.dist-info/top_level.txt
pyaztro-0.3.dist-info/RECORD
