Metadata-Version: 2.1
Name: pyaztro
Version: 0.3
Summary: A client library for aztro - The Astrology API
Home-page: https://github.com/sameerkumar18/pyaztro
Author: Sameer Kumar
Author-email: sam@sameerkumar.website
License: Apache 2.0
Keywords: api wrapper client library astrology data aztro
Platform: UNKNOWN
Classifier: Development Status :: 5 - Production/Stable
Classifier: Intended Audience :: Developers
Classifier: Topic :: Software Development :: Libraries
Classifier: License :: OSI Approved :: Apache Software License
Classifier: Programming Language :: Python
Classifier: Programming Language :: Python :: 2
Classifier: Programming Language :: Python :: 2.7
Classifier: Programming Language :: Python :: 3
Classifier: Programming Language :: Python :: 3.4
Classifier: Programming Language :: Python :: 3.5
Classifier: Programming Language :: Python :: 3.6
Classifier: Programming Language :: Python :: 3.7
Classifier: Programming Language :: Python :: Implementation :: CPython
Classifier: Programming Language :: Python :: Implementation :: PyPy
Provides-Extra: dev
